{
  "openapi": "3.0.1",
  "info": {
    "title": "CourseManagementSystem.API",
    "version": "v1"
  },
  "paths": {
    "/api/Auth/Register": {
      "post": {
        "tags": [
          "Auth"
        ],
        "requestBody": {
          "content": {
            "application/json": {
              "schema": {
                "$ref": "#/components/schemas/RegisterRequestDto"
              }
            },
            "text/json": {
              "schema": {
                "$ref": "#/components/schemas/RegisterRequestDto"
              }
            },
            "application/*+json": {
              "schema": {
                "$ref": "#/components/schemas/RegisterRequestDto"
              }
            }
          }
        },
        "responses": {
          "200": {
            "description": "OK"
          }
        }
      }
    },
    "/api/Auth/confirmEmail": {
      "post": {
        "tags": [
          "Auth"
        ],
        "requestBody": {
          "content": {
            "application/json": {
              "schema": {
                "$ref": "#/components/schemas/ConfirmEmailRequestDto"
              }
            },
            "text/json": {
              "schema": {
                "$ref": "#/components/schemas/ConfirmEmailRequestDto"
              }
            },
            "application/*+json": {
              "schema": {
                "$ref": "#/components/schemas/ConfirmEmailRequestDto"
              }
            }
          }
        },
        "responses": {
          "200": {
            "description": "OK"
          }
        }
      }
    },
    "/api/Auth/ForgetPassword": {
      "post": {
        "tags": [
          "Auth"
        ],
        "requestBody": {
          "content": {
            "application/json": {
              "schema": {
                "$ref": "#/components/schemas/ForgetPasswordDto"
              }
            },
            "text/json": {
              "schema": {
                "$ref": "#/components/schemas/ForgetPasswordDto"
              }
            },
            "application/*+json": {
              "schema": {
                "$ref": "#/components/schemas/ForgetPasswordDto"
              }
            }
          }
        },
        "responses": {
          "200": {
            "description": "OK"
          }
        }
      }
    },
    "/api/Auth/ResetPassword": {
      "post": {
        "tags": [
          "Auth"
        ],
        "requestBody": {
          "content": {
            "application/json": {
              "schema": {
                "$ref": "#/components/schemas/ResetPasswordDto"
              }
            },
            "text/json": {
              "schema": {
                "$ref": "#/components/schemas/ResetPasswordDto"
              }
            },
            "application/*+json": {
              "schema": {
                "$ref": "#/components/schemas/ResetPasswordDto"
              }
            }
          }
        },
        "responses": {
          "200": {
            "description": "OK"
          }
        }
      }
    },
    "/api/Auth/Login": {
      "post": {
        "tags": [
          "Auth"
        ],
        "requestBody": {
          "content": {
            "application/json": {
              "schema": {
                "$ref": "#/components/schemas/LoginRequestDto"
              }
            },
            "text/json": {
              "schema": {
                "$ref": "#/components/schemas/LoginRequestDto"
              }
            },
            "application/*+json": {
              "schema": {
                "$ref": "#/components/schemas/LoginRequestDto"
              }
            }
          }
        },
        "responses": {
          "200": {
            "description": "OK"
          }
        }
      }
    },
    "/api/Auth/refresh-token": {
      "post": {
        "tags": [
          "Auth"
        ],
        "requestBody": {
          "content": {
            "application/json": {
              "schema": {
                "$ref": "#/components/schemas/TokenDto"
              }
            },
            "text/json": {
              "schema": {
                "$ref": "#/components/schemas/TokenDto"
              }
            },
            "application/*+json": {
              "schema": {
                "$ref": "#/components/schemas/TokenDto"
              }
            }
          }
        },
        "responses": {
          "200": {
            "description": "OK"
          }
        }
      }
    },
    "/api/Auth/Me": {
      "get": {
        "tags": [
          "Auth"
        ],
        "responses": {
          "200": {
            "description": "OK"
          }
        }
      }
    },
    "/api/Auth/Update": {
      "put": {
        "tags": [
          "Auth"
        ],
        "requestBody": {
          "content": {
            "application/json": {
              "schema": {
                "$ref": "#/components/schemas/UpdateUserRequestDto"
              }
            },
            "text/json": {
              "schema": {
                "$ref": "#/components/schemas/UpdateUserRequestDto"
              }
            },
            "application/*+json": {
              "schema": {
                "$ref": "#/components/schemas/UpdateUserRequestDto"
              }
            }
          }
        },
        "responses": {
          "200": {
            "description": "OK"
          }
        }
      }
    },
    "/api/Course": {
      "post": {
        "tags": [
          "Course"
        ],
        "requestBody": {
          "content": {
            "application/json": {
              "schema": {
                "$ref": "#/components/schemas/CreateCourseRequestDto"
              }
            },
            "text/json": {
              "schema": {
                "$ref": "#/components/schemas/CreateCourseRequestDto"
              }
            },
            "application/*+json": {
              "schema": {
                "$ref": "#/components/schemas/CreateCourseRequestDto"
              }
            }
          }
        },
        "responses": {
          "200": {
            "description": "OK"
          }
        }
      },
      "get": {
        "tags": [
          "Course"
        ],
        "responses": {
          "200": {
            "description": "OK"
          }
        }
      }
    },
    "/api/Course/{courseId}": {
      "get": {
        "tags": [
          "Course"
        ],
        "parameters": [
          {
            "name": "courseId",
            "in": "path",
            "required": true,
            "schema": {
              "type": "string",
              "format": "uuid"
            }
          }
        ],
        "responses": {
          "200": {
            "description": "OK"
          }
        }
      },
      "put": {
        "tags": [
          "Course"
        ],
        "parameters": [
          {
            "name": "courseId",
            "in": "path",
            "required": true,
            "schema": {
              "type": "string",
              "format": "uuid"
            }
          }
        ],
        "requestBody": {
          "content": {
            "application/json": {
              "schema": {
                "$ref": "#/components/schemas/UpdateCourseRequestDto"
              }
            },
            "text/json": {
              "schema": {
                "$ref": "#/components/schemas/UpdateCourseRequestDto"
              }
            },
            "application/*+json": {
              "schema": {
                "$ref": "#/components/schemas/UpdateCourseRequestDto"
              }
            }
          }
        },
        "responses": {
          "200": {
            "description": "OK"
          }
        }
      },
      "delete": {
        "tags": [
          "Course"
        ],
        "parameters": [
          {
            "name": "courseId",
            "in": "path",
            "required": true,
            "schema": {
              "type": "string",
              "format": "uuid"
            }
          }
        ],
        "responses": {
          "200": {
            "description": "OK"
          }
        }
      }
    },
    "/api/Course/instructor/{instructorId}": {
      "get": {
        "tags": [
          "Course"
        ],
        "parameters": [
          {
            "name": "instructorId",
            "in": "path",
            "required": true,
            "schema": {
              "type": "string"
            }
          }
        ],
        "responses": {
          "200": {
            "description": "OK"
          }
        }
      }
    },
    "/api/Course/{courseId}/enroll": {
      "post": {
        "tags": [
          "Course"
        ],
        "parameters": [
          {
            "name": "courseId",
            "in": "path",
            "required": true,
            "schema": {
              "type": "string",
              "format": "uuid"
            }
          }
        ],
        "responses": {
          "200": {
            "description": "OK"
          }
        }
      }
    },
    "/api/Course/enrolled": {
      "get": {
        "tags": [
          "Course"
        ],
        "responses": {
          "200": {
            "description": "OK"
          }
        }
      }
    },
    "/api/modules/{moduleId}/lessons": {
      "post": {
        "tags": [
          "Lesson"
        ],
        "parameters": [
          {
            "name": "moduleId",
            "in": "path",
            "required": true,
            "schema": {
              "type": "string",
              "format": "uuid"
            }
          }
        ],
        "requestBody": {
          "content": {
            "application/json": {
              "schema": {
                "$ref": "#/components/schemas/CreateLessonRequestDto"
              }
            },
            "text/json": {
              "schema": {
                "$ref": "#/components/schemas/CreateLessonRequestDto"
              }
            },
            "application/*+json": {
              "schema": {
                "$ref": "#/components/schemas/CreateLessonRequestDto"
              }
            }
          }
        },
        "responses": {
          "200": {
            "description": "OK"
          }
        }
      },
      "get": {
        "tags": [
          "Lesson"
        ],
        "parameters": [
          {
            "name": "moduleId",
            "in": "path",
            "required": true,
            "schema": {
              "type": "string",
              "format": "uuid"
            }
          }
        ],
        "responses": {
          "200": {
            "description": "OK"
          }
        }
      }
    },
    "/api/Lesson/{id}": {
      "put": {
        "tags": [
          "Lesson"
        ],
        "parameters": [
          {
            "name": "id",
            "in": "path",
            "required": true,
            "schema": {
              "type": "string",
              "format": "uuid"
            }
          }
        ],
        "requestBody": {
          "content": {
            "application/json": {
              "schema": {
                "$ref": "#/components/schemas/UpdateLessonRequestDto"
              }
            },
            "text/json": {
              "schema": {
                "$ref": "#/components/schemas/UpdateLessonRequestDto"
              }
            },
            "application/*+json": {
              "schema": {
                "$ref": "#/components/schemas/UpdateLessonRequestDto"
              }
            }
          }
        },
        "responses": {
          "200": {
            "description": "OK"
          }
        }
      },
      "delete": {
        "tags": [
          "Lesson"
        ],
        "parameters": [
          {
            "name": "id",
            "in": "path",
            "required": true,
            "schema": {
              "type": "string",
              "format": "uuid"
            }
          }
        ],
        "responses": {
          "200": {
            "description": "OK"
          }
        }
      },
      "get": {
        "tags": [
          "Lesson"
        ],
        "parameters": [
          {
            "name": "id",
            "in": "path",
            "required": true,
            "schema": {
              "type": "string",
              "format": "uuid"
            }
          }
        ],
        "responses": {
          "200": {
            "description": "OK"
          }
        }
      }
    },
    "/api/Module/{courseId}": {
      "post": {
        "tags": [
          "Module"
        ],
        "parameters": [
          {
            "name": "courseId",
            "in": "path",
            "required": true,
            "schema": {
              "type": "string",
              "format": "uuid"
            }
          }
        ],
        "requestBody": {
          "content": {
            "application/json": {
              "schema": {
                "$ref": "#/components/schemas/CreateModuleRequestDto"
              }
            },
            "text/json": {
              "schema": {
                "$ref": "#/components/schemas/CreateModuleRequestDto"
              }
            },
            "application/*+json": {
              "schema": {
                "$ref": "#/components/schemas/CreateModuleRequestDto"
              }
            }
          }
        },
        "responses": {
          "200": {
            "description": "OK"
          }
        }
      }
    },
    "/api/Module/{moduleId}": {
      "get": {
        "tags": [
          "Module"
        ],
        "parameters": [
          {
            "name": "moduleId",
            "in": "path",
            "required": true,
            "schema": {
              "type": "string",
              "format": "uuid"
            }
          }
        ],
        "responses": {
          "200": {
            "description": "OK"
          }
        }
      },
      "put": {
        "tags": [
          "Module"
        ],
        "parameters": [
          {
            "name": "moduleId",
            "in": "path",
            "required": true,
            "schema": {
              "type": "string",
              "format": "uuid"
            }
          }
        ],
        "requestBody": {
          "content": {
            "application/json": {
              "schema": {
                "$ref": "#/components/schemas/UpdateModuleRequestDto"
              }
            },
            "text/json": {
              "schema": {
                "$ref": "#/components/schemas/UpdateModuleRequestDto"
              }
            },
            "application/*+json": {
              "schema": {
                "$ref": "#/components/schemas/UpdateModuleRequestDto"
              }
            }
          }
        },
        "responses": {
          "200": {
            "description": "OK"
          }
        }
      },
      "delete": {
        "tags": [
          "Module"
        ],
        "parameters": [
          {
            "name": "moduleId",
            "in": "path",
            "required": true,
            "schema": {
              "type": "string",
              "format": "uuid"
            }
          }
        ],
        "responses": {
          "200": {
            "description": "OK"
          }
        }
      }
    },
    "/api/Module/courses/{courseId}": {
      "get": {
        "tags": [
          "Module"
        ],
        "parameters": [
          {
            "name": "courseId",
            "in": "path",
            "required": true,
            "schema": {
              "type": "string",
              "format": "uuid"
            }
          }
        ],
        "responses": {
          "200": {
            "description": "OK"
          }
        }
      }
    },
    "/api/Quiz": {
      "post": {
        "tags": [
          "Quiz"
        ],
        "requestBody": {
          "content": {
            "application/json": {
              "schema": {
                "$ref": "#/components/schemas/CreateQuizRequestDto"
              }
            },
            "text/json": {
              "schema": {
                "$ref": "#/components/schemas/CreateQuizRequestDto"
              }
            },
            "application/*+json": {
              "schema": {
                "$ref": "#/components/schemas/CreateQuizRequestDto"
              }
            }
          }
        },
        "responses": {
          "200": {
            "description": "OK"
          }
        }
      }
    },
    "/api/Quiz/{id}": {
      "put": {
        "tags": [
          "Quiz"
        ],
        "parameters": [
          {
            "name": "id",
            "in": "path",
            "required": true,
            "schema": {
              "type": "string",
              "format": "uuid"
            }
          }
        ],
        "requestBody": {
          "content": {
            "application/json": {
              "schema": {
                "$ref": "#/components/schemas/UpdateQuizInfoDto"
              }
            },
            "text/json": {
              "schema": {
                "$ref": "#/components/schemas/UpdateQuizInfoDto"
              }
            },
            "application/*+json": {
              "schema": {
                "$ref": "#/components/schemas/UpdateQuizInfoDto"
              }
            }
          }
        },
        "responses": {
          "200": {
            "description": "OK"
          }
        }
      },
      "get": {
        "tags": [
          "Quiz"
        ],
        "parameters": [
          {
            "name": "id",
            "in": "path",
            "required": true,
            "schema": {
              "type": "string",
              "format": "uuid"
            }
          }
        ],
        "responses": {
          "200": {
            "description": "OK"
          }
        }
      },
      "delete": {
        "tags": [
          "Quiz"
        ],
        "parameters": [
          {
            "name": "id",
            "in": "path",
            "required": true,
            "schema": {
              "type": "string",
              "format": "uuid"
            }
          }
        ],
        "responses": {
          "200": {
            "description": "OK"
          }
        }
      }
    },
    "/api/Quiz/{id}/questions": {
      "post": {
        "tags": [
          "Quiz"
        ],
        "parameters": [
          {
            "name": "id",
            "in": "path",
            "required": true,
            "schema": {
              "type": "string",
              "format": "uuid"
            }
          }
        ],
        "requestBody": {
          "content": {
            "application/json": {
              "schema": {
                "$ref": "#/components/schemas/CreateQuestionRequestDto"
              }
            },
            "text/json": {
              "schema": {
                "$ref": "#/components/schemas/CreateQuestionRequestDto"
              }
            },
            "application/*+json": {
              "schema": {
                "$ref": "#/components/schemas/CreateQuestionRequestDto"
              }
            }
          }
        },
        "responses": {
          "200": {
            "description": "OK"
          }
        }
      },
      "put": {
        "tags": [
          "Quiz"
        ],
        "parameters": [
          {
            "name": "id",
            "in": "path",
            "required": true,
            "schema": {
              "type": "string",
              "format": "uuid"
            }
          }
        ],
        "requestBody": {
          "content": {
            "application/json": {
              "schema": {
                "$ref": "#/components/schemas/UpdateQuizQuestionDto"
              }
            },
            "text/json": {
              "schema": {
                "$ref": "#/components/schemas/UpdateQuizQuestionDto"
              }
            },
            "application/*+json": {
              "schema": {
                "$ref": "#/components/schemas/UpdateQuizQuestionDto"
              }
            }
          }
        },
        "responses": {
          "200": {
            "description": "OK"
          }
        }
      },
      "delete": {
        "tags": [
          "Quiz"
        ],
        "parameters": [
          {
            "name": "id",
            "in": "path",
            "required": true,
            "schema": {
              "type": "string",
              "format": "uuid"
            }
          }
        ],
        "responses": {
          "200": {
            "description": "OK"
          }
        }
      }
    },
    "/api/Video/Upload-Video": {
      "post": {
        "tags": [
          "Video"
        ],
        "parameters": [
          {
            "name": "FileName",
            "in": "query",
            "required": true,
            "schema": {
              "type": "string"
            }
          },
          {
            "name": "Description",
            "in": "query",
            "schema": {
              "type": "string"
            }
          }
        ],
        "requestBody": {
          "content": {
            "multipart/form-data": {
              "schema": {
                "required": [
                  "File"
                ],
                "type": "object",
                "properties": {
                  "File": {
                    "type": "string",
                    "format": "binary"
                  }
                }
              },
              "encoding": {
                "File": {
                  "style": "form"
                }
              }
            }
          }
        },
        "responses": {
          "200": {
            "description": "OK"
          }
        }
      }
    },
    "/api/Video/{Id}": {
      "get": {
        "tags": [
          "Video"
        ],
        "parameters": [
          {
            "name": "Id",
            "in": "path",
            "required": true,
            "schema": {
              "type": "string",
              "format": "uuid"
            }
          }
        ],
        "responses": {
          "200": {
            "description": "OK"
          }
        }
      }
    },
    "/api/Video/{id}": {
      "delete": {
        "tags": [
          "Video"
        ],
        "parameters": [
          {
            "name": "id",
            "in": "path",
            "required": true,
            "schema": {
              "type": "string",
              "format": "uuid"
            }
          }
        ],
        "responses": {
          "200": {
            "description": "OK"
          }
        }
      }
    }
  },
  "components": {
    "schemas": {
      "ConfirmEmailRequestDto": {
        "type": "object",
        "properties": {
          "userId": {
            "type": "string",
            "nullable": true
          },
          "code": {
            "type": "string",
            "nullable": true
          }
        },
        "additionalProperties": false
      },
      "CreateCourseRequestDto": {
        "required": [
          "description",
          "title"
        ],
        "type": "object",
        "properties": {
          "title": {
            "maxLength": 100,
            "minLength": 5,
            "type": "string"
          },
          "description": {
            "maxLength": 1000,
            "minLength": 0,
            "type": "string"
          }
        },
        "additionalProperties": false
      },
      "CreateLessonRequestDto": {
        "type": "object",
        "properties": {
          "title": {
            "type": "string",
            "nullable": true
          },
          "type": {
            "type": "string",
            "nullable": true
          },
          "content": {
            "type": "string",
            "nullable": true
          }
        },
        "additionalProperties": false
      },
      "CreateModuleRequestDto": {
        "required": [
          "title"
        ],
        "type": "object",
        "properties": {
          "title": {
            "maxLength": 100,
            "minLength": 1,
            "type": "string"
          }
        },
        "additionalProperties": false
      },
      "CreateQuestionRequestDto": {
        "type": "object",
        "properties": {
          "question": {
            "type": "string",
            "nullable": true
          },
          "options": {
            "type": "array",
            "items": {
              "type": "string"
            },
            "nullable": true
          },
          "correctAnswer": {
            "type": "string",
            "nullable": true
          }
        },
        "additionalProperties": false
      },
      "CreateQuizRequestDto": {
        "type": "object",
        "properties": {
          "lessonId": {
            "type": "string",
            "format": "uuid"
          }
        },
        "additionalProperties": false
      },
      "ForgetPasswordDto": {
        "type": "object",
        "properties": {
          "email": {
            "type": "string",
            "nullable": true
          }
        },
        "additionalProperties": false
      },
      "LoginRequestDto": {
        "required": [
          "email",
          "password"
        ],
        "type": "object",
        "properties": {
          "email": {
            "minLength": 1,
            "type": "string",
            "format": "email"
          },
          "password": {
            "minLength": 1,
            "type": "string",
            "format": "password"
          }
        },
        "additionalProperties": false
      },
      "RegisterRequestDto": {
        "required": [
          "birthDate",
          "email",
          "gender",
          "name",
          "password"
        ],
        "type": "object",
        "properties": {
          "email": {
            "minLength": 1,
            "type": "string",
            "format": "email"
          },
          "name": {
            "maxLength": 100,
            "minLength": 1,
            "type": "string"
          },
          "gender": {
            "maxLength": 10,
            "minLength": 1,
            "type": "string"
          },
          "birthDate": {
            "type": "string",
            "format": "date"
          },
          "password": {
            "minLength": 1,
            "type": "string",
            "format": "password"
          },
          "roles": {
            "type": "array",
            "items": {
              "type": "string"
            },
            "nullable": true
          }
        },
        "additionalProperties": false
      },
      "ResetPasswordDto": {
        "type": "object",
        "properties": {
          "email": {
            "type": "string",
            "nullable": true
          },
          "code": {
            "type": "string",
            "nullable": true
          },
          "newPassword": {
            "type": "string",
            "nullable": true
          }
        },
        "additionalProperties": false
      },
      "TokenDto": {
        "type": "object",
        "properties": {
          "accessToken": {
            "type": "string",
            "nullable": true
          },
          "refershToken": {
            "type": "string",
            "nullable": true
          }
        },
        "additionalProperties": false
      },
      "UpdateCourseRequestDto": {
        "required": [
          "description",
          "title"
        ],
        "type": "object",
        "properties": {
          "title": {
            "maxLength": 100,
            "minLength": 5,
            "type": "string"
          },
          "description": {
            "maxLength": 1000,
            "minLength": 0,
            "type": "string"
          },
          "createdAt": {
            "type": "string",
            "format": "date-time"
          }
        },
        "additionalProperties": false
      },
      "UpdateLessonRequestDto": {
        "required": [
          "title"
        ],
        "type": "object",
        "properties": {
          "title": {
            "maxLength": 200,
            "minLength": 1,
            "type": "string"
          },
          "content": {
            "type": "string",
            "nullable": true
          }
        },
        "additionalProperties": false
      },
      "UpdateModuleRequestDto": {
        "type": "object",
        "properties": {
          "title": {
            "maxLength": 100,
            "type": "string",
            "nullable": true
          }
        },
        "additionalProperties": false
      },
      "UpdateQuizInfoDto": {
        "type": "object",
        "properties": {
          "lessonId": {
            "type": "string",
            "format": "uuid"
          }
        },
        "additionalProperties": false
      },
      "UpdateQuizQuestionDto": {
        "type": "object",
        "properties": {
          "question": {
            "type": "string",
            "nullable": true
          },
          "options": {
            "type": "array",
            "items": {
              "type": "string"
            },
            "nullable": true
          },
          "correctAnswer": {
            "type": "string",
            "nullable": true
          }
        },
        "additionalProperties": false
      },
      "UpdateUserRequestDto": {
        "type": "object",
        "properties": {
          "name": {
            "type": "string",
            "nullable": true
          },
          "gender": {
            "type": "string",
            "nullable": true
          },
          "birthDate": {
            "type": "string",
            "format": "date-time"
          }
        },
        "additionalProperties": false
      }
    },
    "securitySchemes": {
      "Bearer": {
        "type": "apiKey",
        "name": "Authorization",
        "in": "header"
      }
    }
  },
  "security": [
    {
      "Bearer": [ ]
    }
  ]
}